Metadata-Version: 2.3
Name: evcouplings
Version: 0.2.1
Summary: A Framework for evolutionary couplings analysis
Project-URL: Homepage, https://github.com/debbiemarkslab/EVcouplings
Author-email: Thomas Hopf <thomas.hopf@gmail.com>
License-Expression: MIT
License-File: LICENSE
Keywords: analysis,couplings,evolutionary
Classifier: Development Status :: 4 - Beta
Classifier: Intended Audience :: Developers
Classifier: License :: OSI Approved :: MIT License
Classifier: Programming Language :: Python :: 3
Classifier: Programming Language :: Python :: 3.10
Classifier: Programming Language :: Python :: 3.11
Classifier: Topic :: Scientific/Engineering :: Bio-Informatics
Requires-Dist: billiard
Requires-Dist: biopython>=1.84
Requires-Dist: bokeh
Requires-Dist: click
Requires-Dist: filelock
Requires-Dist: jinja2
Requires-Dist: matplotlib
Requires-Dist: msgpack
Requires-Dist: numba
Requires-Dist: numpy
Requires-Dist: pandas
Requires-Dist: psutil
Requires-Dist: requests
Requires-Dist: ruamel-yaml<0.18
Requires-Dist: scikit-learn
Requires-Dist: scipy
Requires-Dist: seaborn
Requires-Dist: setuptools>=18.2
